{"nodes": [{"id": "users_johanrembeci_desktop_reading_tracker_main_sessioneventrouter2_swift", "label": "SessionEventRouter2.swift", "file_type": "code", "source_file": "SessionEventRouter2.swift", "source_location": "L1"}, {"id": "combine", "label": "Combine", "file_type": "code", "type": "module", "source_file": "SessionEventRouter2.swift", "source_location": "L13"}, {"id": "foundation", "label": "Foundation", "file_type": "code", "type": "module", "source_file": "SessionEventRouter2.swift", "source_location": "L14"}, {"id": "users_johanrembeci_desktop_reading_tracker_main_sessioneventrouter2_sessioneventrouter", "label": "SessionEventRouter", "file_type": "code", "source_file": "SessionEventRouter2.swift", "source_location": "L16", "_callable": true}, {"id": "observableobject", "label": "ObservableObject", "file_type": "code", "source_file": "", "source_location": ""}, {"id": "datastore", "label": "DataStore", "file_type": "code", "source_file": "", "source_location": "", "origin_file": "/Users/johanrembeci/Desktop/Reading Tracker Main /SessionEventRouter2.swift"}, {"id": "behaviorcontextaccesskit", "label": "BehaviorContextAccessKit", "file_type": "code", "source_file": "", "source_location": "", "origin_file": "/Users/johanrembeci/Desktop/Reading Tracker Main /SessionEventRouter2.swift"}, {"id": "behaviorcontextengine", "label": "BehaviorContextEngine", "file_type": "code", "source_file": "", "source_location": "", "origin_file": "/Users/johanrembeci/Desktop/Reading Tracker Main /SessionEventRouter2.swift"}, {"id": "set", "label": "Set", "file_type": "code", "source_file": "", "source_location": "", "origin_file": "/Users/johanrembeci/Desktop/Reading Tracker Main /SessionEventRouter2.swift"}, {"id": "uuid", "label": "UUID", "file_type": "code", "source_file": "", "source_location": "", "origin_file": "/Users/johanrembeci/Desktop/Reading Tracker Main /SessionEventRouter2.swift"}, {"id": "date", "label": "Date", "file_type": "code", "source_file": "", "source_location": "", "origin_file": "/Users/johanrembeci/Desktop/Reading Tracker Main /SessionEventRouter2.swift"}, {"id": "int", "label": "Int", "file_type": "code", "source_file": "", "source_location": "", "origin_file": "/Users/johanrembeci/Desktop/Reading Tracker Main /SessionEventRouter2.swift"}, {"id": "users_johanrembeci_desktop_reading_tracker_main_sessioneventrouter2_sessioneventrouter_init", "label": ".init()", "file_type": "code", "source_file": "SessionEventRouter2.swift", "source_location": "L44", "_callable": true}, {"id": "users_johanrembeci_desktop_reading_tracker_main_sessioneventrouter2_sessioneventrouter_bind", "label": ".bind()", "file_type": "code", "source_file": "SessionEventRouter2.swift", "source_location": "L53", "_callable": true}, {"id": "users_johanrembeci_desktop_reading_tracker_main_sessioneventrouter2_sessioneventrouter_handlebooksupdate", "label": ".handleBooksUpdate()", "file_type": "code", "source_file": "SessionEventRouter2.swift", "source_location": "L78", "_callable": true}, {"id": "book", "label": "Book", "file_type": "code", "source_file": "", "source_location": "", "origin_file": "/Users/johanrembeci/Desktop/Reading Tracker Main /SessionEventRouter2.swift"}, {"id": "users_johanrembeci_desktop_reading_tracker_main_sessioneventrouter2_sessioneventrouter_runpostsessioncascade", "label": ".runPostSessionCascade()", "file_type": "code", "source_file": "SessionEventRouter2.swift", "source_location": "L92", "_callable": true}, {"id": "developerconsoleobservable", "label": "DeveloperConsoleObservable", "file_type": "code", "source_file": "", "source_location": ""}, {"id": "consolesubsystemidentity", "label": "ConsoleSubsystemIdentity", "file_type": "code", "source_file": "", "source_location": "", "origin_file": "/Users/johanrembeci/Desktop/Reading Tracker Main /SessionEventRouter2.swift"}, {"id": "consolesubsystemsnapshot", "label": "ConsoleSubsystemSnapshot", "file_type": "code", "source_file": "", "source_location": "", "origin_file": "/Users/johanrembeci/Desktop/Reading Tracker Main /SessionEventRouter2.swift"}], "edges": [{"source": "users_johanrembeci_desktop_reading_tracker_main_sessioneventrouter2_swift", "target": "combine", "relation": "imports", "context": "import", "confidence": "EXTRACTED", "source_file": "SessionEventRouter2.swift", "source_location": "L13", "weight": 1.0}, {"source": "users_johanrembeci_desktop_reading_tracker_main_sessioneventrouter2_swift", "target": "foundation", "relation": "imports", "context": "import", "confidence": "EXTRACTED", "source_file": "SessionEventRouter2.swift", "source_location": "L14", "weight": 1.0}, {"source": "users_johanrembeci_desktop_reading_tracker_main_sessioneventrouter2_swift", "target": "users_johanrembeci_desktop_reading_tracker_main_sessioneventrouter2_sessioneventrouter", "relation": "contains", "confidence": "EXTRACTED", "source_file": "SessionEventRouter2.swift", "source_location": "L16", "weight": 1.0}, {"source": "users_johanrembeci_desktop_reading_tracker_main_sessioneventrouter2_sessioneventrouter", "target": "observableobject", "relation": "inherits", "confidence": "EXTRACTED", "source_file": "SessionEventRouter2.swift", "source_location": "L16", "weight": 1.0}, {"source": "users_johanrembeci_desktop_reading_tracker_main_sessioneventrouter2_sessioneventrouter", "target": "datastore", "relation": "references", "confidence": "EXTRACTED", "source_file": "SessionEventRouter2.swift", "source_location": "L20", "weight": 1.0, "context": "field"}, {"source": "users_johanrembeci_desktop_reading_tracker_main_sessioneventrouter2_sessioneventrouter", "target": "behaviorcontextaccesskit", "relation": "references", "confidence": "EXTRACTED", "source_file": "SessionEventRouter2.swift", "source_location": "L21", "weight": 1.0, "context": "field"}, {"source": "users_johanrembeci_desktop_reading_tracker_main_sessioneventrouter2_sessioneventrouter", "target": "behaviorcontextengine", "relation": "references", "confidence": "EXTRACTED", "source_file": "SessionEventRouter2.swift", "source_location": "L22", "weight": 1.0, "context": "field"}, {"source": "users_johanrembeci_desktop_reading_tracker_main_sessioneventrouter2_sessioneventrouter", "target": "set", "relation": "references", "confidence": "EXTRACTED", "source_file": "SessionEventRouter2.swift", "source_location": "L26", "weight": 1.0, "context": "field"}, {"source": "users_johanrembeci_desktop_reading_tracker_main_sessioneventrouter2_sessioneventrouter", "target": "uuid", "relation": "references", "confidence": "EXTRACTED", "source_file": "SessionEventRouter2.swift", "source_location": "L26", "weight": 1.0, "context": "generic_arg"}, {"source": "users_johanrembeci_desktop_reading_tracker_main_sessioneventrouter2_sessioneventrouter", "target": "date", "relation": "references", "confidence": "EXTRACTED", "source_file": "SessionEventRouter2.swift", "source_location": "L33", "weight": 1.0, "context": "field"}, {"source": "users_johanrembeci_desktop_reading_tracker_main_sessioneventrouter2_sessioneventrouter", "target": "int", "relation": "references", "confidence": "EXTRACTED", "source_file": "SessionEventRouter2.swift", "source_location": "L34", "weight": 1.0, "context": "field"}, {"source": "users_johanrembeci_desktop_reading_tracker_main_sessioneventrouter2_sessioneventrouter", "target": "users_johanrembeci_desktop_reading_tracker_main_sessioneventrouter2_sessioneventrouter_init", "relation": "method", "confidence": "EXTRACTED", "source_file": "SessionEventRouter2.swift", "source_location": "L44", "weight": 1.0}, {"source": "users_johanrembeci_desktop_reading_tracker_main_sessioneventrouter2_sessioneventrouter", "target": "users_johanrembeci_desktop_reading_tracker_main_sessioneventrouter2_sessioneventrouter_bind", "relation": "method", "confidence": "EXTRACTED", "source_file": "SessionEventRouter2.swift", "source_location": "L53", "weight": 1.0}, {"source": "users_johanrembeci_desktop_reading_tracker_main_sessioneventrouter2_sessioneventrouter_bind", "target": "datastore", "relation": "references", "confidence": "EXTRACTED", "source_file": "SessionEventRouter2.swift", "source_location": "L53", "weight": 1.0, "context": "parameter_type"}, {"source": "users_johanrembeci_desktop_reading_tracker_main_sessioneventrouter2_sessioneventrouter_bind", "target": "behaviorcontextaccesskit", "relation": "references", "confidence": "EXTRACTED", "source_file": "SessionEventRouter2.swift", "source_location": "L53", "weight": 1.0, "context": "parameter_type"}, {"source": "users_johanrembeci_desktop_reading_tracker_main_sessioneventrouter2_sessioneventrouter_bind", "target": "behaviorcontextengine", "relation": "references", "confidence": "EXTRACTED", "source_file": "SessionEventRouter2.swift", "source_location": "L53", "weight": 1.0, "context": "parameter_type"}, {"source": "users_johanrembeci_desktop_reading_tracker_main_sessioneventrouter2_sessioneventrouter", "target": "users_johanrembeci_desktop_reading_tracker_main_sessioneventrouter2_sessioneventrouter_handlebooksupdate", "relation": "method", "confidence": "EXTRACTED", "source_file": "SessionEventRouter2.swift", "source_location": "L78", "weight": 1.0}, {"source": "users_johanrembeci_desktop_reading_tracker_main_sessioneventrouter2_sessioneventrouter_handlebooksupdate", "target": "book", "relation": "references", "confidence": "EXTRACTED", "source_file": "SessionEventRouter2.swift", "source_location": "L78", "weight": 1.0, "context": "parameter_type"}, {"source": "users_johanrembeci_desktop_reading_tracker_main_sessioneventrouter2_sessioneventrouter", "target": "users_johanrembeci_desktop_reading_tracker_main_sessioneventrouter2_sessioneventrouter_runpostsessioncascade", "relation": "method", "confidence": "EXTRACTED", "source_file": "SessionEventRouter2.swift", "source_location": "L92", "weight": 1.0}, {"source": "users_johanrembeci_desktop_reading_tracker_main_sessioneventrouter2_sessioneventrouter_runpostsessioncascade", "target": "book", "relation": "references", "confidence": "EXTRACTED", "source_file": "SessionEventRouter2.swift", "source_location": "L92", "weight": 1.0, "context": "parameter_type"}, {"source": "users_johanrembeci_desktop_reading_tracker_main_sessioneventrouter2_swift", "target": "users_johanrembeci_desktop_reading_tracker_main_sessioneventrouter2_sessioneventrouter", "relation": "contains", "confidence": "EXTRACTED", "source_file": "SessionEventRouter2.swift", "source_location": "L166", "weight": 1.0}, {"source": "users_johanrembeci_desktop_reading_tracker_main_sessioneventrouter2_sessioneventrouter", "target": "developerconsoleobservable", "relation": "implements", "confidence": "EXTRACTED", "source_file": "SessionEventRouter2.swift", "source_location": "L166", "weight": 1.0}, {"source": "users_johanrembeci_desktop_reading_tracker_main_sessioneventrouter2_sessioneventrouter", "target": "consolesubsystemidentity", "relation": "references", "confidence": "EXTRACTED", "source_file": "SessionEventRouter2.swift", "source_location": "L167", "weight": 1.0, "context": "field"}, {"source": "users_johanrembeci_desktop_reading_tracker_main_sessioneventrouter2_sessioneventrouter", "target": "consolesubsystemsnapshot", "relation": "references", "confidence": "EXTRACTED", "source_file": "SessionEventRouter2.swift", "source_location": "L176", "weight": 1.0, "context": "field"}, {"source": "users_johanrembeci_desktop_reading_tracker_main_sessioneventrouter2_sessioneventrouter_bind", "target": "users_johanrembeci_desktop_reading_tracker_main_sessioneventrouter2_sessioneventrouter_handlebooksupdate", "relation": "calls", "context": "call", "confidence": "EXTRACTED", "source_file": "SessionEventRouter2.swift", "source_location": "L71", "weight": 1.0}, {"source": "users_johanrembeci_desktop_reading_tracker_main_sessioneventrouter2_sessioneventrouter_handlebooksupdate", "target": "users_johanrembeci_desktop_reading_tracker_main_sessioneventrouter2_sessioneventrouter_runpostsessioncascade", "relation": "calls", "context": "call", "confidence": "EXTRACTED", "source_file": "SessionEventRouter2.swift", "source_location": "L88", "weight": 1.0}], "raw_calls": [{"caller_nid": "users_johanrembeci_desktop_reading_tracker_main_sessioneventrouter2_sessioneventrouter_init", "callee": "register", "is_member_call": true, "source_file": "SessionEventRouter2.swift", "source_location": "L46", "receiver": "DeveloperConsoleRegistry"}, {"caller_nid": "users_johanrembeci_desktop_reading_tracker_main_sessioneventrouter2_sessioneventrouter_bind", "callee": "store", "is_member_call": true, "source_file": "SessionEventRouter2.swift", "source_location": "L67", "receiver": null}, {"caller_nid": "users_johanrembeci_desktop_reading_tracker_main_sessioneventrouter2_sessioneventrouter_bind", "callee": "sink", "is_member_call": true, "source_file": "SessionEventRouter2.swift", "source_location": "L67", "receiver": null}, {"caller_nid": "users_johanrembeci_desktop_reading_tracker_main_sessioneventrouter2_sessioneventrouter_bind", "callee": "receive", "is_member_call": true, "source_file": "SessionEventRouter2.swift", "source_location": "L67", "receiver": null}, {"caller_nid": "users_johanrembeci_desktop_reading_tracker_main_sessioneventrouter2_sessioneventrouter_bind", "callee": "dropFirst", "is_member_call": true, "source_file": "SessionEventRouter2.swift", "source_location": "L67", "receiver": "dataStore"}, {"caller_nid": "users_johanrembeci_desktop_reading_tracker_main_sessioneventrouter2_sessioneventrouter_handlebooksupdate", "callee": "subtracting", "is_member_call": true, "source_file": "SessionEventRouter2.swift", "source_location": "L82", "receiver": "previouslyActiveBookIDs"}, {"caller_nid": "users_johanrembeci_desktop_reading_tracker_main_sessioneventrouter2_sessioneventrouter_handlebooksupdate", "callee": "Task", "is_member_call": false, "source_file": "SessionEventRouter2.swift", "source_location": "L87", "receiver": null}, {"caller_nid": "users_johanrembeci_desktop_reading_tracker_main_sessioneventrouter2_sessioneventrouter_runpostsessioncascade", "callee": "addingTimeInterval", "is_member_call": true, "source_file": "SessionEventRouter2.swift", "source_location": "L102", "receiver": null}, {"caller_nid": "users_johanrembeci_desktop_reading_tracker_main_sessioneventrouter2_sessioneventrouter_runpostsessioncascade", "callee": "flatMap", "is_member_call": true, "source_file": "SessionEventRouter2.swift", "source_location": "L103", "receiver": "allBooks"}, {"caller_nid": "users_johanrembeci_desktop_reading_tracker_main_sessioneventrouter2_sessioneventrouter_runpostsessioncascade", "callee": "snapshotForCurrentConditions", "is_member_call": true, "source_file": "SessionEventRouter2.swift", "source_location": "L111", "receiver": "WeatherKitService"}, {"caller_nid": "users_johanrembeci_desktop_reading_tracker_main_sessioneventrouter2_sessioneventrouter_runpostsessioncascade", "callee": "evaluate", "is_member_call": true, "source_file": "SessionEventRouter2.swift", "source_location": "L119", "receiver": "IntelligentNotificationEngine"}, {"caller_nid": "users_johanrembeci_desktop_reading_tracker_main_sessioneventrouter2_sessioneventrouter_runpostsessioncascade", "callee": "evaluate", "is_member_call": true, "source_file": "SessionEventRouter2.swift", "source_location": "L129", "receiver": "DataMaturityNotificationAdapter"}, {"caller_nid": "users_johanrembeci_desktop_reading_tracker_main_sessioneventrouter2_sessioneventrouter_runpostsessioncascade", "callee": "schedule", "is_member_call": true, "source_file": "SessionEventRouter2.swift", "source_location": "L131", "receiver": "NotificationScheduler"}, {"caller_nid": "users_johanrembeci_desktop_reading_tracker_main_sessioneventrouter2_sessioneventrouter_runpostsessioncascade", "callee": "flatMap", "is_member_call": true, "source_file": "SessionEventRouter2.swift", "source_location": "L142", "receiver": "allBooks"}, {"caller_nid": "users_johanrembeci_desktop_reading_tracker_main_sessioneventrouter2_sessioneventrouter_runpostsessioncascade", "callee": "readingSessionRecords", "is_member_call": true, "source_file": "SessionEventRouter2.swift", "source_location": "L144", "receiver": "BehaviorEvidenceBuilder"}, {"caller_nid": "users_johanrembeci_desktop_reading_tracker_main_sessioneventrouter2_sessioneventrouter_runpostsessioncascade", "callee": "evidence", "is_member_call": true, "source_file": "SessionEventRouter2.swift", "source_location": "L147", "receiver": "BehaviorEvidenceBuilder"}, {"caller_nid": "users_johanrembeci_desktop_reading_tracker_main_sessioneventrouter2_sessioneventrouter_runpostsessioncascade", "callee": "analyze", "is_member_call": true, "source_file": "SessionEventRouter2.swift", "source_location": "L159", "receiver": "engine"}], "swift_extensions": [{"nid": "users_johanrembeci_desktop_reading_tracker_main_sessioneventrouter2_sessioneventrouter", "label": "SessionEventRouter"}], "swift_type_table": {"path": "/Users/johanrembeci/Desktop/Reading Tracker Main /SessionEventRouter2.swift", "table": {"dataStore": "DataStore", "behaviorKit": "BehaviorContextAccessKit", "contextEngine": "BehaviorContextEngine", "previouslyActiveBookIDs": "Set", "consoleLastCascadeAt": "Date", "consoleCascadeCount": "Int", "books": "Book", "allBooks": "Book", "consoleIdentity": "ConsoleSubsystemIdentity", "consoleSnapshot": "ConsoleSubsystemSnapshot", "currentlyActive": "Set"}}}