{"nodes": [{"id": "users_johanrembeci_desktop_reading_tracker_main_shootingstar_swift", "label": "ShootingStar.swift", "file_type": "code", "source_file": "ShootingStar.swift", "source_location": "L1"}, {"id": "coregraphics", "label": "CoreGraphics", "file_type": "code", "type": "module", "source_file": "ShootingStar.swift", "source_location": "L11"}, {"id": "foundation", "label": "Foundation", "file_type": "code", "type": "module", "source_file": "ShootingStar.swift", "source_location": "L12"}, {"id": "users_johanrembeci_desktop_reading_tracker_main_shootingstar_shootingstar", "label": "ShootingStar", "file_type": "code", "source_file": "ShootingStar.swift", "source_location": "L14", "_callable": true}, {"id": "identifiable", "label": "Identifiable", "file_type": "code", "source_file": "", "source_location": ""}, {"id": "sendable", "label": "Sendable", "file_type": "code", "source_file": "", "source_location": ""}, {"id": "uuid", "label": "UUID", "file_type": "code", "source_file": "", "source_location": "", "origin_file": "/Users/johanrembeci/Desktop/Reading Tracker Main /ShootingStar.swift"}, {"id": "date", "label": "Date", "file_type": "code", "source_file": "", "source_location": "", "origin_file": "/Users/johanrembeci/Desktop/Reading Tracker Main /ShootingStar.swift"}, {"id": "cgpoint", "label": "CGPoint", "file_type": "code", "source_file": "", "source_location": "", "origin_file": "/Users/johanrembeci/Desktop/Reading Tracker Main /ShootingStar.swift"}, {"id": "double", "label": "Double", "file_type": "code", "source_file": "", "source_location": "", "origin_file": "/Users/johanrembeci/Desktop/Reading Tracker Main /ShootingStar.swift"}, {"id": "users_johanrembeci_desktop_reading_tracker_main_shootingstar_shootingstar_randomized", "label": ".randomized()", "file_type": "code", "source_file": "ShootingStar.swift", "source_location": "L38", "_callable": true}, {"id": "cgsize", "label": "CGSize", "file_type": "code", "source_file": "", "source_location": "", "origin_file": "/Users/johanrembeci/Desktop/Reading Tracker Main /ShootingStar.swift"}, {"id": "seededgenerator", "label": "SeededGenerator", "file_type": "code", "source_file": "", "source_location": "", "origin_file": "/Users/johanrembeci/Desktop/Reading Tracker Main /ShootingStar.swift"}], "edges": [{"source": "users_johanrembeci_desktop_reading_tracker_main_shootingstar_swift", "target": "coregraphics", "relation": "imports", "context": "import", "confidence": "EXTRACTED", "source_file": "ShootingStar.swift", "source_location": "L11", "weight": 1.0}, {"source": "users_johanrembeci_desktop_reading_tracker_main_shootingstar_swift", "target": "foundation", "relation": "imports", "context": "import", "confidence": "EXTRACTED", "source_file": "ShootingStar.swift", "source_location": "L12", "weight": 1.0}, {"source": "users_johanrembeci_desktop_reading_tracker_main_shootingstar_swift", "target": "users_johanrembeci_desktop_reading_tracker_main_shootingstar_shootingstar", "relation": "contains", "confidence": "EXTRACTED", "source_file": "ShootingStar.swift", "source_location": "L14", "weight": 1.0}, {"source": "users_johanrembeci_desktop_reading_tracker_main_shootingstar_shootingstar", "target": "identifiable", "relation": "implements", "confidence": "EXTRACTED", "source_file": "ShootingStar.swift", "source_location": "L14", "weight": 1.0}, {"source": "users_johanrembeci_desktop_reading_tracker_main_shootingstar_shootingstar", "target": "sendable", "relation": "implements", "confidence": "EXTRACTED", "source_file": "ShootingStar.swift", "source_location": "L14", "weight": 1.0}, {"source": "users_johanrembeci_desktop_reading_tracker_main_shootingstar_shootingstar", "target": "uuid", "relation": "references", "confidence": "EXTRACTED", "source_file": "ShootingStar.swift", "source_location": "L15", "weight": 1.0, "context": "field"}, {"source": "users_johanrembeci_desktop_reading_tracker_main_shootingstar_shootingstar", "target": "date", "relation": "references", "confidence": "EXTRACTED", "source_file": "ShootingStar.swift", "source_location": "L19", "weight": 1.0, "context": "field"}, {"source": "users_johanrembeci_desktop_reading_tracker_main_shootingstar_shootingstar", "target": "cgpoint", "relation": "references", "confidence": "EXTRACTED", "source_file": "ShootingStar.swift", "source_location": "L22", "weight": 1.0, "context": "field"}, {"source": "users_johanrembeci_desktop_reading_tracker_main_shootingstar_shootingstar", "target": "cgpoint", "relation": "references", "confidence": "EXTRACTED", "source_file": "ShootingStar.swift", "source_location": "L26", "weight": 1.0, "context": "field"}, {"source": "users_johanrembeci_desktop_reading_tracker_main_shootingstar_shootingstar", "target": "double", "relation": "references", "confidence": "EXTRACTED", "source_file": "ShootingStar.swift", "source_location": "L28", "weight": 1.0, "context": "field"}, {"source": "users_johanrembeci_desktop_reading_tracker_main_shootingstar_shootingstar", "target": "double", "relation": "references", "confidence": "EXTRACTED", "source_file": "ShootingStar.swift", "source_location": "L32", "weight": 1.0, "context": "field"}, {"source": "users_johanrembeci_desktop_reading_tracker_main_shootingstar_shootingstar", "target": "double", "relation": "references", "confidence": "EXTRACTED", "source_file": "ShootingStar.swift", "source_location": "L36", "weight": 1.0, "context": "field"}, {"source": "users_johanrembeci_desktop_reading_tracker_main_shootingstar_shootingstar", "target": "users_johanrembeci_desktop_reading_tracker_main_shootingstar_shootingstar_randomized", "relation": "method", "confidence": "EXTRACTED", "source_file": "ShootingStar.swift", "source_location": "L38", "weight": 1.0}, {"source": "users_johanrembeci_desktop_reading_tracker_main_shootingstar_shootingstar_randomized", "target": "cgsize", "relation": "references", "confidence": "EXTRACTED", "source_file": "ShootingStar.swift", "source_location": "L38", "weight": 1.0, "context": "parameter_type"}, {"source": "users_johanrembeci_desktop_reading_tracker_main_shootingstar_shootingstar_randomized", "target": "seededgenerator", "relation": "references", "confidence": "EXTRACTED", "source_file": "ShootingStar.swift", "source_location": "L38", "weight": 1.0, "context": "parameter_type"}, {"source": "users_johanrembeci_desktop_reading_tracker_main_shootingstar_shootingstar_randomized", "target": "date", "relation": "references", "confidence": "EXTRACTED", "source_file": "ShootingStar.swift", "source_location": "L38", "weight": 1.0, "context": "parameter_type"}, {"source": "users_johanrembeci_desktop_reading_tracker_main_shootingstar_shootingstar_randomized", "target": "users_johanrembeci_desktop_reading_tracker_main_shootingstar_shootingstar", "relation": "references", "confidence": "EXTRACTED", "source_file": "ShootingStar.swift", "source_location": "L38", "weight": 1.0, "context": "return_type"}, {"source": "users_johanrembeci_desktop_reading_tracker_main_shootingstar_shootingstar_randomized", "target": "cgpoint", "relation": "calls", "context": "call", "confidence": "EXTRACTED", "source_file": "ShootingStar.swift", "source_location": "L46", "weight": 1.0}, {"source": "users_johanrembeci_desktop_reading_tracker_main_shootingstar_shootingstar_randomized", "target": "users_johanrembeci_desktop_reading_tracker_main_shootingstar_shootingstar", "relation": "calls", "context": "call", "confidence": "EXTRACTED", "source_file": "ShootingStar.swift", "source_location": "L68", "weight": 1.0}, {"source": "users_johanrembeci_desktop_reading_tracker_main_shootingstar_shootingstar_randomized", "target": "uuid", "relation": "calls", "context": "call", "confidence": "EXTRACTED", "source_file": "ShootingStar.swift", "source_location": "L69", "weight": 1.0}], "raw_calls": [{"caller_nid": "users_johanrembeci_desktop_reading_tracker_main_shootingstar_shootingstar_randomized", "callee": "random", "is_member_call": true, "source_file": "ShootingStar.swift", "source_location": "L42", "receiver": "Int"}, {"caller_nid": "users_johanrembeci_desktop_reading_tracker_main_shootingstar_shootingstar_randomized", "callee": "random", "is_member_call": true, "source_file": "ShootingStar.swift", "source_location": "L46", "receiver": "Double"}, {"caller_nid": "users_johanrembeci_desktop_reading_tracker_main_shootingstar_shootingstar_randomized", "callee": "random", "is_member_call": true, "source_file": "ShootingStar.swift", "source_location": "L48", "receiver": "Double"}, {"caller_nid": "users_johanrembeci_desktop_reading_tracker_main_shootingstar_shootingstar_randomized", "callee": "random", "is_member_call": true, "source_file": "ShootingStar.swift", "source_location": "L50", "receiver": "Double"}, {"caller_nid": "users_johanrembeci_desktop_reading_tracker_main_shootingstar_shootingstar_randomized", "callee": "random", "is_member_call": true, "source_file": "ShootingStar.swift", "source_location": "L55", "receiver": "Double"}, {"caller_nid": "users_johanrembeci_desktop_reading_tracker_main_shootingstar_shootingstar_randomized", "callee": "random", "is_member_call": true, "source_file": "ShootingStar.swift", "source_location": "L58", "receiver": "Double"}, {"caller_nid": "users_johanrembeci_desktop_reading_tracker_main_shootingstar_shootingstar_randomized", "callee": "cos", "is_member_call": false, "source_file": "ShootingStar.swift", "source_location": "L60", "receiver": null}, {"caller_nid": "users_johanrembeci_desktop_reading_tracker_main_shootingstar_shootingstar_randomized", "callee": "sin", "is_member_call": false, "source_file": "ShootingStar.swift", "source_location": "L61", "receiver": null}, {"caller_nid": "users_johanrembeci_desktop_reading_tracker_main_shootingstar_shootingstar_randomized", "callee": "clamp", "is_member_call": true, "source_file": "ShootingStar.swift", "source_location": "L64", "receiver": "EnvironmentMath"}, {"caller_nid": "users_johanrembeci_desktop_reading_tracker_main_shootingstar_shootingstar_randomized", "callee": "clamp", "is_member_call": true, "source_file": "ShootingStar.swift", "source_location": "L65", "receiver": "EnvironmentMath"}, {"caller_nid": "users_johanrembeci_desktop_reading_tracker_main_shootingstar_shootingstar_randomized", "callee": "random", "is_member_call": true, "source_file": "ShootingStar.swift", "source_location": "L73", "receiver": "Double"}, {"caller_nid": "users_johanrembeci_desktop_reading_tracker_main_shootingstar_shootingstar_randomized", "callee": "random", "is_member_call": true, "source_file": "ShootingStar.swift", "source_location": "L74", "receiver": "Double"}, {"caller_nid": "users_johanrembeci_desktop_reading_tracker_main_shootingstar_shootingstar_randomized", "callee": "random", "is_member_call": true, "source_file": "ShootingStar.swift", "source_location": "L75", "receiver": "Double"}], "swift_type_table": {"path": "/Users/johanrembeci/Desktop/Reading Tracker Main /ShootingStar.swift", "table": {"id": "UUID", "spawnDate": "Date", "start": "CGPoint", "end": "CGPoint", "brightness": "Double", "duration": "Double", "fadeRate": "Double", "fieldSize": "CGSize", "generator": "SeededGenerator"}}}